streamlit_widget_tracker/__init__.py
streamlit_widget_tracker-0.1.2.dist-info/METADATA
streamlit_widget_tracker-0.1.2.dist-info/WHEEL
streamlit_widget_tracker-0.1.2.dist-info/top_level.txt
streamlit_widget_tracker-0.1.2.dist-info/RECORD
