Metadata-Version: 2.1
Name: streamlit-widget-tracker
Version: 0.1.2
Summary: streamlit-widget-tracker helps track the widget values in use
Home-page: https://github.com/PROFESSOR-PENGUIN/streamlit-widget-tracker
Author: Ashish Rai
Author-email: ashishraics512@gmail.com
License: MIT
Platform: UNKNOWN
Requires-Python: >=3.6
Requires-Dist: streamlit (>=0.63)
Requires-Dist: streamlit-text-like (>=0.0.2)
